abcloud/__init__.py
abcloud/abcloud.py
abcloud/version.py
abcloud/utils/__init__.py
abcloud/utils/cluster.py
abcloud/utils/config.py
abcloud/utils/ec2utils.py
abcloud-0.2.7.data/scripts/abcloud
abcloud-0.2.7.dist-info/LICENSE
abcloud-0.2.7.dist-info/METADATA
abcloud-0.2.7.dist-info/WHEEL
abcloud-0.2.7.dist-info/top_level.txt
abcloud-0.2.7.dist-info/RECORD
